MainContent/BasicMath.py
MainContent/__init__.py
MainContent-0.1.dist-info/LICENSE
MainContent-0.1.dist-info/METADATA
MainContent-0.1.dist-info/WHEEL
MainContent-0.1.dist-info/top_level.txt
MainContent-0.1.dist-info/RECORD
